interface_frame/__init__.py
interface_frame/asserts.py
interface_frame/common.py
interface_frame/db.py
interface_frame/ddt.py
interface_frame/decorators.py
interface_frame/exceptions.py
interface_frame/http_request.py
interface_frame/mail.py
interface_frame/my_thread.py
interface_frame/num_util.py
interface_frame/runner.py
interface_frame/se_common.py
interface_frame/task_job.py
interface_frame/task_scheduler.py
interface_frame/template.py
interface_frame/test_case.py
interface_frame/test_suite.py
interface_frame/utils.py
interface_frame/xmind_util.py
interface_frame/log/__init__.py
interface_frame/log/config.py
interface_frame/log/handlers.py
interface_frame/skeleton/README.md
interface_frame/skeleton/requirements.txt
interface_frame/skeleton/conf/global.json
interface_frame/skeleton/conf/pro.json
interface_frame/skeleton/conf/readme.md
interface_frame/skeleton/conf/scheduler.json
interface_frame/skeleton/conf/test.json
interface_frame/skeleton/conf/uat.json
interface_frame/skeleton/conf/bbbb/demo2.json
interface_frame/skeleton/testcases/assert_demo.py
interface_frame/skeleton/testcases/demo1.py
interface_frame/skeleton/testcases/html_demo.py
interface_frame/skeleton/testcases/idl_demo.py
interface_frame/skeleton/testcases/readme.md
interface_frame/skeleton/testcases/run_test_suite.py
interface_frame/skeleton/testcases/测试场景/idl_demo.py
interface_frame/skeleton/testcases/测试场景/readme.md
interface_frame/skeleton/testcases/测试物料/demo1.py
interface_frame/skeleton/testcases/测试物料/readme.md
interface_frame/templates/idl.json
interface_frame/templates/test_case_report.html
interface_frame/templates/test_suite_report.html
interface_frame_SDK-1.0.3.dist-info/METADATA
interface_frame_SDK-1.0.3.dist-info/WHEEL
interface_frame_SDK-1.0.3.dist-info/top_level.txt
interface_frame_SDK-1.0.3.dist-info/RECORD
